caca/__init__.py
caca/caca.py
mm_calc_1-0.0.1.dist-info/METADATA
mm_calc_1-0.0.1.dist-info/WHEEL
mm_calc_1-0.0.1.dist-info/top_level.txt
mm_calc_1-0.0.1.dist-info/RECORD
