Metadata-Version: 2.1
Name: mm-calc-1
Version: 0.0.1
Summary: This is test calculator for my Turing College project version 2
Author: Martin Macak
Author-email: <martinmacak@protonmail.com>
Keywords: python,calculator,learning,turing college
Classifier: Development Status :: 1 - Planning
Classifier: Intended Audience :: Developers
Classifier: Programming Language :: Python :: 3
Classifier: Operating System :: Unix
Classifier: Operating System :: MacOS :: MacOS X
Classifier: Operating System :: Microsoft :: Windows
